nomad_camels_driver_demo_instrument/demo_instrument.py
nomad_camels_driver_demo_instrument/demo_instrument_ophyd.py
nomad_camels_driver_demo_instrument-0.1.1.dist-info/LICENSE.txt
nomad_camels_driver_demo_instrument-0.1.1.dist-info/METADATA
nomad_camels_driver_demo_instrument-0.1.1.dist-info/WHEEL
nomad_camels_driver_demo_instrument-0.1.1.dist-info/top_level.txt
nomad_camels_driver_demo_instrument-0.1.1.dist-info/RECORD
